{"siteId":"11693","siteName":"Stribers Farm","waterbody":"GB112073071260","totalSurveys":1,"species":[{"code":"3-spined stickleback","name":"3-spined stickleback (Gasterosteus aculeatus)","unit":"count","data":[{"timestamp":780105600000,"value":0}]},{"code":"Brown / sea trout","name":"Brown / sea trout (Salmo trutta)","unit":"count","data":[{"timestamp":780105600000,"value":36}]},{"code":"European eels > elvers","name":"European eels > elvers (Anguilla anguilla)","unit":"count","data":[{"timestamp":780105600000,"value":0}]}]}