{"siteId":"12738","siteName":"Redlake Farm","waterbody":"GB108052021170","totalSurveys":1,"species":[{"code":"10-spined stickleback","name":"10-spined stickleback (Pungitius pungitius)","unit":"count","data":[{"timestamp":685324800000,"value":57}]},{"code":"3-spined stickleback","name":"3-spined stickleback (Gasterosteus aculeatus)","unit":"count","data":[{"timestamp":685324800000,"value":19}]},{"code":"European eel","name":"European eel (Anguilla anguilla)","unit":"count","data":[{"timestamp":685324800000,"value":8}]}]}