{"siteId":"14600","siteName":"Wood Farm Off Stream Refuge","waterbody":"GB109054050200","totalSurveys":2,"species":[{"code":"Brook lamprey","name":"Brook lamprey (Lampetra planeri)","unit":"count","data":[{"timestamp":1212624000000,"value":0}]},{"code":"Chub","name":"Chub (Leuciscus cephalus)","unit":"count","data":[{"timestamp":1117065600000,"value":2},{"timestamp":1212624000000,"value":5}]},{"code":"Common bream","name":"Common bream (Abramis brama)","unit":"count","data":[{"timestamp":1117065600000,"value":6},{"timestamp":1212624000000,"value":6}]},{"code":"Dace","name":"Dace (Leuciscus leuciscus)","unit":"count","data":[{"timestamp":1117065600000,"value":7},{"timestamp":1212624000000,"value":4}]},{"code":"Minnow","name":"Minnow (Phoxinus phoxinus)","unit":"count","data":[{"timestamp":1117065600000,"value":0}]},{"code":"Perch","name":"Perch (Perca fluviatilis)","unit":"count","data":[{"timestamp":1117065600000,"value":9},{"timestamp":1212624000000,"value":8}]},{"code":"Pike","name":"Pike (Esox lucius)","unit":"count","data":[{"timestamp":1212624000000,"value":2}]},{"code":"Roach","name":"Roach (Rutilus rutilus)","unit":"count","data":[{"timestamp":1117065600000,"value":23},{"timestamp":1212624000000,"value":53}]}]}