{"siteId":"1777","siteName":"Belaugh Broad","waterbody":"GB105034050930","totalSurveys":2,"species":[{"code":"Gudgeon","name":"Gudgeon (Gobio gobio)","unit":"count","data":[{"timestamp":752889600000,"value":2}]},{"code":"Perch","name":"Perch (Perca fluviatilis)","unit":"count","data":[{"timestamp":752889600000,"value":1},{"timestamp":821059200000,"value":2}]},{"code":"Pike","name":"Pike (Esox lucius)","unit":"count","data":[{"timestamp":752889600000,"value":1}]},{"code":"Ruffe","name":"Ruffe (Gymnocephalus cernuus)","unit":"count","data":[{"timestamp":752889600000,"value":1}]}]}