{"siteId":"31889","siteName":"Crown Fishery (Dobb's Lock + Carthagena)","waterbody":"GB106038077851","totalSurveys":1,"species":[{"code":"Chub","name":"Chub (Leuciscus cephalus)","unit":"count","data":[{"timestamp":728870400000,"value":1}]},{"code":"Common bream","name":"Common bream (Abramis brama)","unit":"count","data":[{"timestamp":728870400000,"value":1}]},{"code":"Common carp varieties","name":"Common carp varieties (Cyprinus carpio)","unit":"count","data":[{"timestamp":728870400000,"value":1}]},{"code":"European eel","name":"European eel (Anguilla anguilla)","unit":"count","data":[{"timestamp":728870400000,"value":1}]},{"code":"Perch","name":"Perch (Perca fluviatilis)","unit":"count","data":[{"timestamp":728870400000,"value":12}]},{"code":"Pike varieties","name":"Pike varieties (Esox lucius)","unit":"count","data":[{"timestamp":728870400000,"value":7}]},{"code":"Roach","name":"Roach (Rutilus rutilus)","unit":"count","data":[{"timestamp":728870400000,"value":1}]},{"code":"Tench varieties","name":"Tench varieties (Tinca tinca)","unit":"count","data":[{"timestamp":728870400000,"value":7}]}]}