{"siteId":"34543","siteName":"Larch Close","waterbody":"GB104027062780","totalSurveys":3,"species":[{"code":"Brown / sea trout","name":"Brown / sea trout (Salmo trutta)","unit":"count","data":[{"timestamp":1252368000000,"value":57},{"timestamp":1439424000000,"value":19},{"timestamp":1630454400000,"value":54}]},{"code":"Bullhead","name":"Bullhead (Cottus gobio)","unit":"count","data":[{"timestamp":1252368000000,"value":12},{"timestamp":1439424000000,"value":38},{"timestamp":1630454400000,"value":23}]}]}