{"siteId":"4503","siteName":"P.B.I (Trumpington Meadows)","waterbody":"GB105033037600","totalSurveys":11,"species":[{"code":"3-spined stickleback","name":"3-spined stickleback (Gasterosteus aculeatus)","unit":"count","data":[{"timestamp":850867200000,"value":2},{"timestamp":1277942400000,"value":1}]},{"code":"Brook lamprey","name":"Brook lamprey (Lampetra planeri)","unit":"count","data":[{"timestamp":1109030400000,"value":1},{"timestamp":1277942400000,"value":3},{"timestamp":1289433600000,"value":1}]},{"code":"Brown / sea trout","name":"Brown / sea trout (Salmo trutta)","unit":"count","data":[{"timestamp":1277942400000,"value":8},{"timestamp":1289433600000,"value":6},{"timestamp":1374796800000,"value":7}]},{"code":"Bullhead","name":"Bullhead (Cottus gobio)","unit":"count","data":[{"timestamp":1268697600000,"value":21},{"timestamp":1277942400000,"value":2},{"timestamp":1289433600000,"value":11},{"timestamp":1374796800000,"value":4},{"timestamp":1562803200000,"value":2},{"timestamp":1742342400000,"value":0}]},{"code":"Chub","name":"Chub (Leuciscus cephalus)","unit":"count","data":[{"timestamp":673574400000,"value":8},{"timestamp":748483200000,"value":23},{"timestamp":1109030400000,"value":3},{"timestamp":1221609600000,"value":1},{"timestamp":1374796800000,"value":12},{"timestamp":1562803200000,"value":9},{"timestamp":1742342400000,"value":11}]},{"code":"Common bream","name":"Common bream (Abramis brama)","unit":"count","data":[{"timestamp":673574400000,"value":1}]},{"code":"Dace","name":"Dace (Leuciscus leuciscus)","unit":"count","data":[{"timestamp":673574400000,"value":58},{"timestamp":748483200000,"value":1},{"timestamp":1374796800000,"value":11},{"timestamp":1562803200000,"value":15},{"timestamp":1742342400000,"value":1}]},{"code":"European eel","name":"European eel (Anguilla anguilla)","unit":"count","data":[{"timestamp":1277942400000,"value":2}]},{"code":"European eels > elvers","name":"European eels > elvers (Anguilla anguilla)","unit":"count","data":[{"timestamp":673574400000,"value":5},{"timestamp":748483200000,"value":7},{"timestamp":1221609600000,"value":2},{"timestamp":1289433600000,"value":1},{"timestamp":1742342400000,"value":1}]},{"code":"Gudgeon","name":"Gudgeon (Gobio gobio)","unit":"count","data":[{"timestamp":673574400000,"value":21},{"timestamp":748483200000,"value":18},{"timestamp":850867200000,"value":5},{"timestamp":1109030400000,"value":3},{"timestamp":1221609600000,"value":1},{"timestamp":1268697600000,"value":3},{"timestamp":1277942400000,"value":3},{"timestamp":1289433600000,"value":5},{"timestamp":1374796800000,"value":2}]},{"code":"Minnow","name":"Minnow (Phoxinus phoxinus)","unit":"count","data":[{"timestamp":748483200000,"value":1},{"timestamp":850867200000,"value":1},{"timestamp":1221609600000,"value":7},{"timestamp":1268697600000,"value":47},{"timestamp":1277942400000,"value":33},{"timestamp":1289433600000,"value":18},{"timestamp":1374796800000,"value":46},{"timestamp":1562803200000,"value":8}]},{"code":"Perch","name":"Perch (Perca fluviatilis)","unit":"count","data":[{"timestamp":673574400000,"value":20},{"timestamp":748483200000,"value":51},{"timestamp":850867200000,"value":7},{"timestamp":1109030400000,"value":1},{"timestamp":1221609600000,"value":4},{"timestamp":1277942400000,"value":4},{"timestamp":1289433600000,"value":1},{"timestamp":1374796800000,"value":6},{"timestamp":1562803200000,"value":7},{"timestamp":1742342400000,"value":3}]},{"code":"Pike","name":"Pike (Esox lucius)","unit":"count","data":[{"timestamp":673574400000,"value":24},{"timestamp":748483200000,"value":25},{"timestamp":850867200000,"value":10},{"timestamp":1109030400000,"value":4},{"timestamp":1221609600000,"value":4},{"timestamp":1289433600000,"value":2},{"timestamp":1374796800000,"value":4},{"timestamp":1562803200000,"value":6}]},{"code":"Roach","name":"Roach (Rutilus rutilus)","unit":"count","data":[{"timestamp":673574400000,"value":727},{"timestamp":748483200000,"value":267},{"timestamp":1221609600000,"value":2},{"timestamp":1374796800000,"value":10},{"timestamp":1562803200000,"value":11}]},{"code":"Roach x common bream hybrid","name":"Roach x common bream hybrid (Rutilus rutilus x Abramis brama)","unit":"count","data":[{"timestamp":673574400000,"value":2}]},{"code":"Rudd","name":"Rudd (Scardinius erythrophthalmus)","unit":"count","data":[{"timestamp":673574400000,"value":1}]},{"code":"Ruffe","name":"Ruffe (Gymnocephalus cernuus)","unit":"count","data":[{"timestamp":748483200000,"value":2}]},{"code":"Spined loach","name":"Spined loach (Cobitis taenia)","unit":"count","data":[{"timestamp":850867200000,"value":2},{"timestamp":1109030400000,"value":5},{"timestamp":1221609600000,"value":1},{"timestamp":1268697600000,"value":7},{"timestamp":1277942400000,"value":2},{"timestamp":1289433600000,"value":4},{"timestamp":1374796800000,"value":6}]},{"code":"Stone loach","name":"Stone loach (Barbatula barbatula)","unit":"count","data":[{"timestamp":1109030400000,"value":1},{"timestamp":1268697600000,"value":3},{"timestamp":1277942400000,"value":14},{"timestamp":1374796800000,"value":6}]}]}