{"siteId":"4666","siteName":"DS Stow Bridge","waterbody":"GB105033047660","totalSurveys":10,"species":[{"code":"10-spined stickleback","name":"10-spined stickleback (Pungitius pungitius)","unit":"count","data":[{"timestamp":1316131200000,"value":2},{"timestamp":1404950400000,"value":1}]},{"code":"3-spined stickleback","name":"3-spined stickleback (Gasterosteus aculeatus)","unit":"count","data":[{"timestamp":1316131200000,"value":3}]},{"code":"Bleak","name":"Bleak (Alburnus alburnus)","unit":"count","data":[{"timestamp":686448000000,"value":25}]},{"code":"Brook lamprey","name":"Brook lamprey (Lampetra planeri)","unit":"count","data":[{"timestamp":1404950400000,"value":1}]},{"code":"Bullhead","name":"Bullhead (Cottus gobio)","unit":"count","data":[{"timestamp":1316131200000,"value":1},{"timestamp":1404950400000,"value":7},{"timestamp":1502150400000,"value":1}]},{"code":"Common [wild] carp","name":"Common [wild] carp (Cyprinus carpio)","unit":"count","data":[{"timestamp":1123718400000,"value":1}]},{"code":"Common bream","name":"Common bream (Abramis brama)","unit":"count","data":[{"timestamp":589680000000,"value":1},{"timestamp":686448000000,"value":26},{"timestamp":747532800000,"value":168},{"timestamp":843177600000,"value":626},{"timestamp":967766400000,"value":18},{"timestamp":1219104000000,"value":34},{"timestamp":1316131200000,"value":11},{"timestamp":1404950400000,"value":3},{"timestamp":1502150400000,"value":207}]},{"code":"Dace","name":"Dace (Leuciscus leuciscus)","unit":"count","data":[{"timestamp":686448000000,"value":5},{"timestamp":967766400000,"value":1}]},{"code":"European eels > elvers","name":"European eels > elvers (Anguilla anguilla)","unit":"count","data":[{"timestamp":686448000000,"value":1},{"timestamp":747532800000,"value":2},{"timestamp":843177600000,"value":1},{"timestamp":967766400000,"value":1},{"timestamp":1404950400000,"value":2}]},{"code":"Flounder","name":"Flounder (Platichthys flesus)","unit":"count","data":[{"timestamp":589680000000,"value":2},{"timestamp":686448000000,"value":1},{"timestamp":747532800000,"value":6},{"timestamp":843177600000,"value":1},{"timestamp":967766400000,"value":4}]},{"code":"Gudgeon","name":"Gudgeon (Gobio gobio)","unit":"count","data":[{"timestamp":589680000000,"value":1},{"timestamp":1316131200000,"value":1},{"timestamp":1502150400000,"value":1}]},{"code":"Perch","name":"Perch (Perca fluviatilis)","unit":"count","data":[{"timestamp":589680000000,"value":3},{"timestamp":747532800000,"value":132},{"timestamp":843177600000,"value":180},{"timestamp":967766400000,"value":43},{"timestamp":1123718400000,"value":141},{"timestamp":1219104000000,"value":1},{"timestamp":1316131200000,"value":148},{"timestamp":1404950400000,"value":61},{"timestamp":1502150400000,"value":494}]},{"code":"Pike","name":"Pike (Esox lucius)","unit":"count","data":[{"timestamp":589680000000,"value":1},{"timestamp":686448000000,"value":1},{"timestamp":843177600000,"value":2},{"timestamp":1316131200000,"value":1},{"timestamp":1404950400000,"value":2}]},{"code":"Roach","name":"Roach (Rutilus rutilus)","unit":"count","data":[{"timestamp":589680000000,"value":7},{"timestamp":686448000000,"value":201},{"timestamp":747532800000,"value":4467},{"timestamp":843177600000,"value":110},{"timestamp":967766400000,"value":157},{"timestamp":1123718400000,"value":46},{"timestamp":1219104000000,"value":142},{"timestamp":1316131200000,"value":37},{"timestamp":1404950400000,"value":87},{"timestamp":1502150400000,"value":95}]},{"code":"Roach x common bream hybrid","name":"Roach x common bream hybrid (Rutilus rutilus x Abramis brama)","unit":"count","data":[{"timestamp":686448000000,"value":4},{"timestamp":747532800000,"value":18},{"timestamp":843177600000,"value":6},{"timestamp":967766400000,"value":4},{"timestamp":1123718400000,"value":2},{"timestamp":1316131200000,"value":4},{"timestamp":1502150400000,"value":3}]},{"code":"Ruffe","name":"Ruffe (Gymnocephalus cernuus)","unit":"count","data":[{"timestamp":589680000000,"value":20},{"timestamp":686448000000,"value":3},{"timestamp":747532800000,"value":27},{"timestamp":843177600000,"value":1},{"timestamp":967766400000,"value":10},{"timestamp":1219104000000,"value":2},{"timestamp":1316131200000,"value":3},{"timestamp":1404950400000,"value":2},{"timestamp":1502150400000,"value":1}]},{"code":"Silver bream","name":"Silver bream (Abramis bjoerkna)","unit":"count","data":[{"timestamp":686448000000,"value":6},{"timestamp":747532800000,"value":4},{"timestamp":843177600000,"value":15},{"timestamp":967766400000,"value":2}]},{"code":"Smelt","name":"Smelt (Osmerus eperlanus)","unit":"count","data":[{"timestamp":589680000000,"value":6},{"timestamp":686448000000,"value":21}]},{"code":"Spined loach","name":"Spined loach (Cobitis taenia)","unit":"count","data":[{"timestamp":1219104000000,"value":1},{"timestamp":1404950400000,"value":4}]},{"code":"Tench","name":"Tench (Tinca tinca)","unit":"count","data":[{"timestamp":747532800000,"value":1},{"timestamp":967766400000,"value":1},{"timestamp":1316131200000,"value":1},{"timestamp":1404950400000,"value":1},{"timestamp":1502150400000,"value":2}]},{"code":"Zander","name":"Zander (Sander lucioperca)","unit":"count","data":[{"timestamp":589680000000,"value":2},{"timestamp":686448000000,"value":127},{"timestamp":747532800000,"value":49},{"timestamp":843177600000,"value":80},{"timestamp":967766400000,"value":3},{"timestamp":1404950400000,"value":16},{"timestamp":1502150400000,"value":4}]}]}