{"siteId":"4844","siteName":"Warren Farm","waterbody":"GB105033047791","totalSurveys":7,"species":[{"code":"3-spined stickleback","name":"3-spined stickleback (Gasterosteus aculeatus)","unit":"count","data":[{"timestamp":1270598400000,"value":1}]},{"code":"Brown / sea trout","name":"Brown / sea trout (Salmo trutta)","unit":"count","data":[{"timestamp":627004800000,"value":47},{"timestamp":731894400000,"value":45},{"timestamp":822355200000,"value":71},{"timestamp":1047600000000,"value":20},{"timestamp":1175126400000,"value":51},{"timestamp":1270598400000,"value":14},{"timestamp":1332979200000,"value":36}]},{"code":"Bullhead","name":"Bullhead (Cottus gobio)","unit":"count","data":[{"timestamp":627004800000,"value":1},{"timestamp":1047600000000,"value":11},{"timestamp":1175126400000,"value":4},{"timestamp":1270598400000,"value":5},{"timestamp":1332979200000,"value":27}]},{"code":"Dace","name":"Dace (Leuciscus leuciscus)","unit":"count","data":[{"timestamp":731894400000,"value":1}]},{"code":"European eel","name":"European eel (Anguilla anguilla)","unit":"count","data":[{"timestamp":1047600000000,"value":15},{"timestamp":1270598400000,"value":13}]},{"code":"European eels > elvers","name":"European eels > elvers (Anguilla anguilla)","unit":"count","data":[{"timestamp":627004800000,"value":281},{"timestamp":731894400000,"value":122},{"timestamp":822355200000,"value":40},{"timestamp":1175126400000,"value":15},{"timestamp":1332979200000,"value":74}]},{"code":"Pike","name":"Pike (Esox lucius)","unit":"count","data":[{"timestamp":627004800000,"value":1},{"timestamp":1270598400000,"value":2},{"timestamp":1332979200000,"value":2}]},{"code":"Rainbow trout","name":"Rainbow trout (Oncorhynchus mykiss)","unit":"count","data":[{"timestamp":822355200000,"value":2}]},{"code":"Rudd","name":"Rudd (Scardinius erythrophthalmus)","unit":"count","data":[{"timestamp":731894400000,"value":1}]}]}