{"siteId":"50379","siteName":"R. Rye at Duncombe Park above Sink Hole","waterbody":"GB104027068200","totalSurveys":1,"species":[{"code":"Brown / sea trout","name":"Brown / sea trout (Salmo trutta)","unit":"count","data":[{"timestamp":1377561600000,"value":36}]},{"code":"Bullhead","name":"Bullhead (Cottus gobio)","unit":"count","data":[{"timestamp":1377561600000,"value":48}]},{"code":"Stone loach","name":"Stone loach (Barbatula barbatula)","unit":"count","data":[{"timestamp":1377561600000,"value":4}]}]}