{"siteId":"55243","siteName":"US Walsworth Common","waterbody":"GB105033037690","totalSurveys":1,"species":[{"code":"10-spined stickleback","name":"10-spined stickleback (Pungitius pungitius)","unit":"count","data":[{"timestamp":1395792000000,"value":2}]},{"code":"3-spined stickleback","name":"3-spined stickleback (Gasterosteus aculeatus)","unit":"count","data":[{"timestamp":1395792000000,"value":92}]},{"code":"Bullhead","name":"Bullhead (Cottus gobio)","unit":"count","data":[{"timestamp":1395792000000,"value":32}]}]}