{"siteId":"6136","siteName":"D/S Harrowden Weir","waterbody":"GB105032045140","totalSurveys":6,"species":[{"code":"Bullhead","name":"Bullhead (Cottus gobio)","unit":"count","data":[{"timestamp":697161600000,"value":2},{"timestamp":798422400000,"value":2},{"timestamp":900374400000,"value":7},{"timestamp":994723200000,"value":0},{"timestamp":1146700800000,"value":0}]},{"code":"Chub","name":"Chub (Leuciscus cephalus)","unit":"count","data":[{"timestamp":601862400000,"value":55},{"timestamp":697161600000,"value":15},{"timestamp":798422400000,"value":134},{"timestamp":900374400000,"value":98},{"timestamp":994723200000,"value":40},{"timestamp":1146700800000,"value":40}]},{"code":"Common [wild] carp","name":"Common [wild] carp (Cyprinus carpio)","unit":"count","data":[{"timestamp":900374400000,"value":1}]},{"code":"Dace","name":"Dace (Leuciscus leuciscus)","unit":"count","data":[{"timestamp":601862400000,"value":11},{"timestamp":697161600000,"value":21},{"timestamp":798422400000,"value":25},{"timestamp":900374400000,"value":6},{"timestamp":1146700800000,"value":5}]},{"code":"European eels > elvers","name":"European eels > elvers (Anguilla anguilla)","unit":"count","data":[{"timestamp":798422400000,"value":1},{"timestamp":900374400000,"value":3},{"timestamp":994723200000,"value":1},{"timestamp":1146700800000,"value":1}]},{"code":"Gudgeon","name":"Gudgeon (Gobio gobio)","unit":"count","data":[{"timestamp":601862400000,"value":22},{"timestamp":697161600000,"value":9},{"timestamp":798422400000,"value":23},{"timestamp":900374400000,"value":21},{"timestamp":994723200000,"value":2},{"timestamp":1146700800000,"value":15}]},{"code":"Minnow","name":"Minnow (Phoxinus phoxinus)","unit":"count","data":[{"timestamp":697161600000,"value":1},{"timestamp":798422400000,"value":20},{"timestamp":900374400000,"value":6},{"timestamp":994723200000,"value":0},{"timestamp":1146700800000,"value":0}]},{"code":"Mirror carp","name":"Mirror carp (Cyprinus carpio)","unit":"count","data":[{"timestamp":900374400000,"value":1}]},{"code":"Perch","name":"Perch (Perca fluviatilis)","unit":"count","data":[{"timestamp":601862400000,"value":2},{"timestamp":798422400000,"value":11},{"timestamp":900374400000,"value":3},{"timestamp":994723200000,"value":5}]},{"code":"Pike","name":"Pike (Esox lucius)","unit":"count","data":[{"timestamp":601862400000,"value":16},{"timestamp":697161600000,"value":7},{"timestamp":798422400000,"value":3},{"timestamp":900374400000,"value":12},{"timestamp":994723200000,"value":2}]},{"code":"Roach","name":"Roach (Rutilus rutilus)","unit":"count","data":[{"timestamp":601862400000,"value":81},{"timestamp":697161600000,"value":100},{"timestamp":798422400000,"value":61},{"timestamp":900374400000,"value":109},{"timestamp":994723200000,"value":7},{"timestamp":1146700800000,"value":51}]},{"code":"Stone loach","name":"Stone loach (Barbatula barbatula)","unit":"count","data":[{"timestamp":798422400000,"value":2},{"timestamp":994723200000,"value":0}]},{"code":"Tench","name":"Tench (Tinca tinca)","unit":"count","data":[{"timestamp":601862400000,"value":1},{"timestamp":900374400000,"value":3}]}]}