{"siteId":"72284","siteName":"Marchamley Pools","waterbody":null,"totalSurveys":1,"species":[{"code":"Common [wild] carp","name":"Common [wild] carp (Cyprinus carpio)","unit":"count","data":[{"timestamp":1571788800000,"value":7}]},{"code":"Common bream","name":"Common bream (Abramis brama)","unit":"count","data":[{"timestamp":1571788800000,"value":500}]},{"code":"Mirror carp","name":"Mirror carp (Cyprinus carpio)","unit":"count","data":[{"timestamp":1571788800000,"value":7}]},{"code":"Perch","name":"Perch (Perca fluviatilis)","unit":"count","data":[{"timestamp":1571788800000,"value":26}]},{"code":"Roach","name":"Roach (Rutilus rutilus)","unit":"count","data":[{"timestamp":1571788800000,"value":60}]},{"code":"Wels catfish","name":"Wels catfish (Silurus glanis)","unit":"count","data":[{"timestamp":1571788800000,"value":6}]}]}