{"siteId":"8129","siteName":"Downstream Salterwath Bridge","waterbody":"GB112072071720","totalSurveys":5,"species":[{"code":"Atlantic salmon","name":"Atlantic salmon (Salmo salar)","unit":"count","data":[{"timestamp":395971200000,"value":114},{"timestamp":426816000000,"value":31},{"timestamp":457315200000,"value":106},{"timestamp":682300800000,"value":68},{"timestamp":1030406400000,"value":28}]},{"code":"Brown / sea trout","name":"Brown / sea trout (Salmo trutta)","unit":"count","data":[{"timestamp":395971200000,"value":9},{"timestamp":426816000000,"value":19},{"timestamp":457315200000,"value":26},{"timestamp":682300800000,"value":2},{"timestamp":1030406400000,"value":13}]},{"code":"Bullhead","name":"Bullhead (Cottus gobio)","unit":"count","data":[{"timestamp":682300800000,"value":0}]},{"code":"European eel","name":"European eel (Anguilla anguilla)","unit":"count","data":[{"timestamp":682300800000,"value":3}]},{"code":"Minnow","name":"Minnow (Phoxinus phoxinus)","unit":"count","data":[{"timestamp":682300800000,"value":0}]},{"code":"Stone loach","name":"Stone loach (Barbatula barbatula)","unit":"count","data":[{"timestamp":682300800000,"value":0}]}]}