{"siteId":"8412","siteName":"Lower Langdon","waterbody":"GB108048007650","totalSurveys":33,"species":[{"code":"Atlantic salmon","name":"Atlantic salmon (Salmo salar)","unit":"count","data":[{"timestamp":240105600000,"value":5},{"timestamp":262483200000,"value":2},{"timestamp":266457600000,"value":0},{"timestamp":271555200000,"value":2},{"timestamp":275529600000,"value":1},{"timestamp":773539200000,"value":5},{"timestamp":834796800000,"value":10},{"timestamp":873676800000,"value":21},{"timestamp":965779200000,"value":14},{"timestamp":1029888000000,"value":9},{"timestamp":1061856000000,"value":41},{"timestamp":1093910400000,"value":10},{"timestamp":1122854400000,"value":47},{"timestamp":1154390400000,"value":6},{"timestamp":1185840000000,"value":11},{"timestamp":1216252800000,"value":9},{"timestamp":1249948800000,"value":11},{"timestamp":1277683200000,"value":6},{"timestamp":1339977600000,"value":30},{"timestamp":1404950400000,"value":56},{"timestamp":1467676800000,"value":39},{"timestamp":1501804800000,"value":51},{"timestamp":1531180800000,"value":13},{"timestamp":1568678400000,"value":23},{"timestamp":1628035200000,"value":2},{"timestamp":1657065600000,"value":3},{"timestamp":1689724800000,"value":3},{"timestamp":1720051200000,"value":1}]},{"code":"Brown / sea trout","name":"Brown / sea trout (Salmo trutta)","unit":"count","data":[{"timestamp":240105600000,"value":68},{"timestamp":262483200000,"value":186},{"timestamp":266457600000,"value":136},{"timestamp":271555200000,"value":100},{"timestamp":275529600000,"value":78},{"timestamp":294537600000,"value":221},{"timestamp":299203200000,"value":126},{"timestamp":302832000000,"value":115},{"timestamp":308534400000,"value":111},{"timestamp":773539200000,"value":51},{"timestamp":834796800000,"value":97},{"timestamp":873676800000,"value":84},{"timestamp":965779200000,"value":69},{"timestamp":1029888000000,"value":96},{"timestamp":1061856000000,"value":83},{"timestamp":1093910400000,"value":54},{"timestamp":1122854400000,"value":98},{"timestamp":1154390400000,"value":60},{"timestamp":1185840000000,"value":54},{"timestamp":1216252800000,"value":39},{"timestamp":1249948800000,"value":52},{"timestamp":1277683200000,"value":104},{"timestamp":1339977600000,"value":72},{"timestamp":1404950400000,"value":109},{"timestamp":1467676800000,"value":72},{"timestamp":1501804800000,"value":81},{"timestamp":1531180800000,"value":160},{"timestamp":1568678400000,"value":129},{"timestamp":1628035200000,"value":141},{"timestamp":1657065600000,"value":127},{"timestamp":1689724800000,"value":73},{"timestamp":1720051200000,"value":64},{"timestamp":1753833600000,"value":92}]},{"code":"Bullhead","name":"Bullhead (Cottus gobio)","unit":"count","data":[{"timestamp":240105600000,"value":125},{"timestamp":262483200000,"value":0},{"timestamp":266457600000,"value":386},{"timestamp":271555200000,"value":0},{"timestamp":275529600000,"value":0},{"timestamp":294537600000,"value":283},{"timestamp":299203200000,"value":202},{"timestamp":302832000000,"value":308},{"timestamp":308534400000,"value":297},{"timestamp":773539200000,"value":0},{"timestamp":834796800000,"value":0},{"timestamp":873676800000,"value":102},{"timestamp":965779200000,"value":64},{"timestamp":1029888000000,"value":0},{"timestamp":1061856000000,"value":121},{"timestamp":1093910400000,"value":52},{"timestamp":1122854400000,"value":0},{"timestamp":1154390400000,"value":46},{"timestamp":1185840000000,"value":0},{"timestamp":1216252800000,"value":0},{"timestamp":1249948800000,"value":0},{"timestamp":1277683200000,"value":40},{"timestamp":1339977600000,"value":123},{"timestamp":1404950400000,"value":84},{"timestamp":1467676800000,"value":8},{"timestamp":1501804800000,"value":186},{"timestamp":1531180800000,"value":29},{"timestamp":1568678400000,"value":59},{"timestamp":1628035200000,"value":23},{"timestamp":1657065600000,"value":21},{"timestamp":1689724800000,"value":35},{"timestamp":1720051200000,"value":7},{"timestamp":1753833600000,"value":4}]},{"code":"European eel","name":"European eel (Anguilla anguilla)","unit":"count","data":[{"timestamp":262483200000,"value":2},{"timestamp":266457600000,"value":0},{"timestamp":271555200000,"value":3},{"timestamp":773539200000,"value":0},{"timestamp":834796800000,"value":0},{"timestamp":1216252800000,"value":0}]},{"code":"European eels > elvers","name":"European eels > elvers (Anguilla anguilla)","unit":"count","data":[{"timestamp":299203200000,"value":2},{"timestamp":302832000000,"value":3},{"timestamp":308534400000,"value":1},{"timestamp":965779200000,"value":1},{"timestamp":1154390400000,"value":1},{"timestamp":1249948800000,"value":0},{"timestamp":1628035200000,"value":1},{"timestamp":1657065600000,"value":1}]},{"code":"Minnow","name":"Minnow (Phoxinus phoxinus)","unit":"count","data":[{"timestamp":240105600000,"value":52},{"timestamp":262483200000,"value":0},{"timestamp":266457600000,"value":0},{"timestamp":271555200000,"value":0},{"timestamp":275529600000,"value":0},{"timestamp":294537600000,"value":139},{"timestamp":299203200000,"value":76},{"timestamp":302832000000,"value":84},{"timestamp":308534400000,"value":128},{"timestamp":773539200000,"value":0},{"timestamp":834796800000,"value":0},{"timestamp":873676800000,"value":0},{"timestamp":965779200000,"value":0},{"timestamp":1029888000000,"value":0},{"timestamp":1093910400000,"value":0},{"timestamp":1122854400000,"value":0},{"timestamp":1185840000000,"value":0},{"timestamp":1216252800000,"value":0},{"timestamp":1249948800000,"value":0},{"timestamp":1467676800000,"value":1},{"timestamp":1501804800000,"value":16},{"timestamp":1531180800000,"value":5},{"timestamp":1568678400000,"value":45},{"timestamp":1628035200000,"value":16},{"timestamp":1657065600000,"value":18},{"timestamp":1720051200000,"value":1},{"timestamp":1753833600000,"value":2}]}]}