{"siteId":"8625","siteName":"Elmhurst A","waterbody":"GB105030062450","totalSurveys":2,"species":[{"code":"Chub","name":"Chub (Leuciscus cephalus)","unit":"count","data":[{"timestamp":503539200000,"value":2}]},{"code":"Common [wild] carp","name":"Common [wild] carp (Cyprinus carpio)","unit":"count","data":[{"timestamp":1037664000000,"value":5}]},{"code":"Common bream","name":"Common bream (Abramis brama)","unit":"count","data":[{"timestamp":503539200000,"value":499},{"timestamp":1037664000000,"value":604}]},{"code":"Dace","name":"Dace (Leuciscus leuciscus)","unit":"count","data":[{"timestamp":503539200000,"value":1}]},{"code":"Ghost carp","name":"Ghost carp (Cyprinus carpio)","unit":"count","data":[{"timestamp":1037664000000,"value":16}]},{"code":"Golden orfe","name":"Golden orfe (Leuciscus idus)","unit":"count","data":[{"timestamp":1037664000000,"value":1}]},{"code":"Leather carp","name":"Leather carp (Cyprinus carpio)","unit":"count","data":[{"timestamp":1037664000000,"value":2}]},{"code":"Mirror carp","name":"Mirror carp (Cyprinus carpio)","unit":"count","data":[{"timestamp":1037664000000,"value":23}]},{"code":"Perch","name":"Perch (Perca fluviatilis)","unit":"count","data":[{"timestamp":503539200000,"value":178},{"timestamp":1037664000000,"value":179}]},{"code":"Pike","name":"Pike (Esox lucius)","unit":"count","data":[{"timestamp":503539200000,"value":5}]},{"code":"Roach","name":"Roach (Rutilus rutilus)","unit":"count","data":[{"timestamp":503539200000,"value":2535},{"timestamp":1037664000000,"value":2475}]},{"code":"Roach x common bream hybrid","name":"Roach x common bream hybrid (Rutilus rutilus x Abramis brama)","unit":"count","data":[{"timestamp":1037664000000,"value":77}]},{"code":"Rudd","name":"Rudd (Scardinius erythrophthalmus)","unit":"count","data":[{"timestamp":1037664000000,"value":129}]},{"code":"Silver bream","name":"Silver bream (Abramis bjoerkna)","unit":"count","data":[{"timestamp":503539200000,"value":4},{"timestamp":1037664000000,"value":18}]},{"code":"Tench","name":"Tench (Tinca tinca)","unit":"count","data":[{"timestamp":1037664000000,"value":3}]}]}