{"ammonia":{"dates":["2026-01-16","2026-02-02"],"values":[0.03,0.03]},"do_percent":{"dates":["2026-01-16","2026-02-02"],"values":[97.6,97.7]},"nitrate":{"dates":["2026-01-16","2026-02-02"],"values":[5.09,5.6]},"ph":{"dates":["2026-01-16","2026-02-02"],"values":[7.8,7.9]},"phosphate":{"dates":["2026-01-16","2026-02-02"],"values":[0.033,0.026]},"ss":{"dates":["2026-01-16","2026-02-02"],"values":[13.0,21.0]},"temperature":{"dates":["2026-01-16","2026-02-02"],"values":[8.0,9.4]},"total_oxidised_n":{"dates":["2026-01-16","2026-02-02"],"values":[5.1,5.6]}}